byquantlib/__init__.py
byquantlib/bybacktest.py
byquantlib/bystrategy.py
byquantlib/help.py
byquantlib/setting.py
byquantlib/analysis/__init__.py
byquantlib/analysis/byanalysis.py
byquantlib/auth/__init__.py
byquantlib/auth/byauth.py
byquantlib/chart/__init__.py
byquantlib/chart/matplotlib.py
byquantlib/chart/mplfinance.py
byquantlib/chart/seaborn.py
byquantlib/data/__init__.py
byquantlib/data/get.py
byquantlib/lib/__init__.py
byquantlib/lib/backtest.py
byquantlib/lib/bymetrics.py
byquantlib/lib/sharpe_drawdown_return.py
byquantlib/pyarmor_runtime_009273/__init__.py
byquantlib/pyarmor_runtime_009273/pyarmor_runtime.pyd
byquantlib/store/__init__.py
byquantlib/techanaly/__init__.py
byquantlib/techanaly/ad.py
byquantlib/techanaly/adosc.py
byquantlib/techanaly/adx.py
byquantlib/techanaly/adxr.py
byquantlib/techanaly/apo.py
byquantlib/techanaly/aroon.py
byquantlib/techanaly/aroonosc.py
byquantlib/techanaly/ash.py
byquantlib/techanaly/atr.py
byquantlib/techanaly/avgprice.py
byquantlib/techanaly/bbands.py
byquantlib/techanaly/beta.py
byquantlib/techanaly/bop.py
byquantlib/techanaly/cci.py
byquantlib/techanaly/cdl2crows.py
byquantlib/techanaly/cdl3whitesoldiers.py
byquantlib/techanaly/cdldarkcloudcover.py
byquantlib/techanaly/cdldragonflydoji.py
byquantlib/techanaly/cdleveningstar.py
byquantlib/techanaly/cdlmorningstar.py
byquantlib/techanaly/cmo.py
byquantlib/techanaly/correl.py
byquantlib/techanaly/dema.py
byquantlib/techanaly/donchian.py
byquantlib/techanaly/dx.py
byquantlib/techanaly/ema.py
byquantlib/techanaly/highest.py
byquantlib/techanaly/ht_dcperiod.py
byquantlib/techanaly/ht_dcphase.py
byquantlib/techanaly/ht_phasor.py
byquantlib/techanaly/ht_sine.py
byquantlib/techanaly/ht_trendmode.py
byquantlib/techanaly/kama.py
byquantlib/techanaly/kdj.py
byquantlib/techanaly/linearreg.py
byquantlib/techanaly/linearreg_angle.py
byquantlib/techanaly/linearreg_intercept.py
byquantlib/techanaly/linearreg_slope.py
byquantlib/techanaly/lowest.py
byquantlib/techanaly/ma.py
byquantlib-3.12.76.0.dist-info/METADATA
byquantlib-3.12.76.0.dist-info/WHEEL
byquantlib-3.12.76.0.dist-info/top_level.txt
byquantlib-3.12.76.0.dist-info/RECORD
